arackpy/__init__.py
arackpy/spider.py
arackpy/utils.py
arackpy/backends/__init__.py
arackpy/backends/backend_beautifulsoup.py
arackpy/backends/backend_default.py
arackpy/backends/backend_selenium.py
arackpy/backends/backend_tor.py
arackpy-0.1.0a1.data/data/LICENSE.txt
arackpy-0.1.0a1.data/data/README
scripts/__init__.py
scripts/publish_pypi.py
scripts/setup.py
scripts/test_pypi.py
tests/__init__.py
tests/basetest.py
tests/test_spider.py
arackpy-0.1.0a1.dist-info/LICENSE.txt
arackpy-0.1.0a1.dist-info/METADATA
arackpy-0.1.0a1.dist-info/WHEEL
arackpy-0.1.0a1.dist-info/top_level.txt
arackpy-0.1.0a1.dist-info/RECORD
