Metadata-Version: 2.1
Name: arackpy
Version: 0.1.0a1
Summary: A multithreaded webcrawler and scraper
Home-page: https://www.bitbucket.com/denisgomes/arackpy
Author: Denis Gomes
Author-email: denis.mp.gomes@gmail.com
License: BSD
Keywords: web crawler scraper
Platform: UNKNOWN
Classifier: Programming Language :: Python
Classifier: Programming Language :: Python :: 2
Classifier: Programming Language :: Python :: 2.7
Classifier: Programming Language :: Python :: 3
Classifier: Programming Language :: Python :: 3.6
